polargini/__init__.py
polargini/cli.py
polargini/io.py
polargini/metrics.py
polargini/pgc.py
polargini/plotting.py
polargini/preprocessing.py
polargini/stats.py
polargini-1.0.0.dist-info/licenses/LICENSE
polargini-1.0.0.dist-info/METADATA
polargini-1.0.0.dist-info/WHEEL
polargini-1.0.0.dist-info/entry_points.txt
polargini-1.0.0.dist-info/top_level.txt
polargini-1.0.0.dist-info/RECORD
